depthcryption/__init__.py
depthcryption/cryptors_cryptors.py
depthcryption/cryptors_tools.py
depthcryption/key_handler_cache.py
depthcryption/simple_lookups.py
depthcryption/step_manager.py
depthcryption/tools_exceptions.py
depthcryption/tools_utils.py
depthcryption/user_functions.py
depthcryption/version.py
depthcryption/sls/__init__.py
depthcryption/sls/simple_lookups_310.py
depthcryption/sls/simple_lookups_311.py
depthcryption/sls/simple_lookups_312.py
depthcryption/sls/simple_lookups_39.py
depthcryption/tests/__init__.py
depthcryption/tests/test_run_all.py
depthcryption-0.0.1.1.dist-info/LICENSE
depthcryption-0.0.1.1.dist-info/METADATA
depthcryption-0.0.1.1.dist-info/WHEEL
depthcryption-0.0.1.1.dist-info/top_level.txt
depthcryption-0.0.1.1.dist-info/RECORD
