Metadata-Version: 2.1
Name: depthcryption
Version: 0.0.1.1
Summary: A bleeding edge encryption package that offers a powerful never-before-seen approach to encryption with an impressive suite of features in easy to use functions.
Home-page: https://github.com/mw-os/DepthCryption
Author: Mitchell Williams
Requires-Python: >=3.9
License-File: LICENSE
